macaw_auth/__init__.py
macaw_auth/main.py
macaw_auth/classes/__init__.py
macaw_auth/classes/configuration.py
macaw_auth/classes/idp_connection.py
macaw_auth/classes/sts_saml.py
macaw_auth/classes/user_credentials.py
macaw_auth/classes/username_validation.py
macaw_auth/functions/__init__.py
macaw_auth/functions/assume_role.py
macaw_auth/functions/common.py
macaw_auth/functions/login.py
macaw_auth/functions/web_logon.py
macaw_auth-2.1.0.dist-info/licenses/LICENSE
macaw_auth-2.1.0.dist-info/METADATA
macaw_auth-2.1.0.dist-info/WHEEL
macaw_auth-2.1.0.dist-info/entry_points.txt
macaw_auth-2.1.0.dist-info/top_level.txt
macaw_auth-2.1.0.dist-info/RECORD
