Metadata-Version: 2.4
Name: macaw-auth
Version: 2.1.0
Summary: Utility to authenticate to AWS Services via CLI using ADFS
Author-email: Travis Samuel <tsamuel@alum.mit.edu>
License-Expression: MIT
Project-URL: Homepage, https://github.com/tsamuel33/macaw-auth
Project-URL: Bug Tracker, https://github.com/tsamuel33/macaw-auth/issues
Classifier: Programming Language :: Python :: 3
Classifier: Operating System :: OS Independent
Requires-Python: >3.7
License-File: LICENSE
Requires-Dist: requests
Requires-Dist: requests_ntlm
Requires-Dist: beautifulsoup4
Requires-Dist: boto3
Requires-Dist: keyring
Dynamic: license-file
